{
  "schemaVersion": 1,
  "id": "config_despawn",
  "version": "${version}",
  "name": "Configurable Item Despawn",
  "description": "Adds an option to change how long it takes an item to despawn.",
  "authors": [
    "Rhyhe"
  ],
  "contact": {
    "homepage": "",
    "sources": ""
  },
  "icon": "icon.png",
  "license": "CC0-1.0",
  "environment": "*",
  "entrypoints": {
    "main": [
      "rhyhe.config_despawn.ConfigDespawn"
    ],
    "beforeGameStart": [
      "rhyhe.config_despawn.ConfigDespawn"
    ],
    "afterGameStart": [
      "rhyhe.config_despawn.ConfigDespawn"
    ],
    "recipesReady": [
      "rhyhe.config_despawn.ConfigDespawn"
    ]
  },
  "mixins": [
    "config_despawn.mixins.json"
  ],
  "depends": {
    "minecraft": "^7.2-beta",
    "fabricloader": ">=0.15.5"
  },
  "suggests": {
  }
}
